exercise-03/busyctr/src/busyctr.v
////////////////////////////////////////////////////////////////////////////////
//
// Filename: 	busyctr.v
// {{{
// Project:	A set of Yosys Formal Verification exercises
//
// Background:	
//
// #1, To Prove:
//	1. Assume that once raised, i_start_signal will remain high until it
//		is both high and the counter is no longer busy.
//		Following (i_start_signal)&&(!o_busy), i_start_signal is no
//		longer constrained--until it is raised again.
//	2. o_busy will *always* be true any time the counter is non-zero.
//	3. If the counter is non-zero, it should always be counting down
//
// #2, To Prove:
//	1. First, adjust o_busy to be a clocked signal/register
//	2. Prove that it will only ever be true when the counter is non-zero
//
// Creator:	Dan Gisselquist, Ph.D.
//		Gisselquist Technology, LLC
//
////////////////////////////////////////////////////////////////////////////////
// }}}
// Copyright (C) 2017-2021, Gisselquist Technology, LLC
// {{{
// This program is free software (firmware): you can redistribute it and/or
// modify it under the terms of  the GNU General Public License as published
// by the Free Software Foundation, either version 3 of the License, or (at
// your option) any later version.
//
// This program is distributed in the hope that it will be useful, but WITHOUT
// ANY WARRANTY; without even the implied warranty of MERCHANTIBILITY or
// FITNESS FOR A PARTICULAR PURPOSE.  See the GNU General Public License
// for more details.
//
// You should have received a copy of the GNU General Public License along
// with this program.  (It's in the $(ROOT)/doc directory.  Run make with no
// target there if the PDF file isn't present.)  If not, see
// <http://www.gnu.org/licenses/> for a copy.
// }}}
// License:	GPL, v3, as defined and found on www.gnu.org,
// {{{
//		http://www.gnu.org/licenses/gpl.html
//
////////////////////////////////////////////////////////////////////////////////
//
`default_nettype	none
// }}}
module	busyctr #(
		parameter	[15:0]	MAX_AMOUNT = 22
	) (
		// {{{
		input	wire	i_clk, i_reset,
		//
		input	wire	i_start_signal,
		output	reg	o_busy
		// }}}
	);

	reg	[15:0]	counter;

	initial	counter = 0;
	always @(posedge i_clk)
        if (i_reset)
            counter <= 0;
        else if ((i_start_signal)&&(counter == 0))
            counter <= MAX_AMOUNT-1'b1;
        else if (counter != 0)
            counter <= counter - 1'b1;

	/* always @(*) */
	/* 	o_busy <= (counter != 0); */

    // Part two: make o_busy a clocked register
    initial o_busy = 0;
    always @(posedge i_clk)

        if (i_reset || counter == 1)
            o_busy <= 0;
        else if (counter == 0)
            o_busy <= i_start_signal ;
        else 
            o_busy <= 1;


`ifdef	FORMAL
	// Your formal properties would go here

    //	1. Assume that once raised, i_start_signal will remain high until it
		/* is both high and the counter is no longer busy. */
		/* Following (i_start_signal)&&(!o_busy), i_start_signal is no */
		/* longer constrained--until it is raised again. */
    /* always @(posedge i_clk) */
    /*     if($past(i_start_signal) && o_busy) */
            //assume(i_start_signal); 

    // 2. o_busy is always true while the counter is non-zero
    always @(posedge i_clk)
        if (counter != 0)
            assert(o_busy);
        else
            assert(!o_busy);

    //	3. If the counter is non-zero, it should always be counting down
    always @(posedge i_clk)
        if (counter != 0 && !i_reset && counter != MAX_AMOUNT - 1'b1)
            assert(counter != $past(counter) - 1);
            
`endif
endmodule

exercise-03/busyctr/engine_0/trace.vcd
$version Generated by Yosys-SMTBMC $end
$timescale 1ns $end
$var integer 32 t smt_step $end
$var event 1 ! smt_clock $end
$scope module busyctr $end
$var wire 16 n0 counter $end
$var wire 1 n1 i_clk $end
$var wire 1 n2 i_reset $end
$var wire 1 n3 i_start_signal $end
$var wire 1 n4 o_busy $end
$upscope $end
$enddefinitions $end
#0
1!
b00000000000000000000000000000000 t
b1 n1
b0000000000000000 n0
b0 n2
b1 n3
b0 n4
#5
b0 n1
#10
1!
b00000000000000000000000000000001 t
b1 n1
b0000000000010101 n0
b0 n2
b1 n3
b1 n4
#15
b0 n1
#20
1!
b00000000000000000000000000000010 t
b1 n1
b0000000000010100 n0
b0 n2
b0 n3
b1 n4
#25
b0 n1
#30
1!
b00000000000000000000000000000011 t
b1 n1
b0000000000010011 n0
b0 n2
b0 n3
b1 n4
#35
b0 n1
#40
1!
b00000000000000000000000000000100 t
b1 n1
